code_manager/__init__.py
code_manager/main.py
code_manager/merge_packages_lists.py
code_manager/version.py
code_manager/commands/__init__.py
code_manager/commands/command.py
code_manager/commands/commit.py
code_manager/commands/find.py
code_manager/commands/grep.py
code_manager/commands/pull.py
code_manager/commands/push.py
code_manager/commands/root.py
code_manager/commands/sed.py
code_manager/core/__init__.py
code_manager/core/cache_container.py
code_manager/core/command_container.py
code_manager/core/configuration.py
code_manager/core/deb_dependency.py
code_manager/core/debgrapher.py
code_manager/core/fetcher.py
code_manager/core/installation.py
code_manager/core/manager.py
code_manager/data/cache
code_manager/data/conf
code_manager/data/packages.json
code_manager/install_scripts/install_i3gaps.sh
code_manager/install_scripts/install_rxvt-unicode.sh
code_manager/installers/__init__.py
code_manager/installers/autoreconf.py
code_manager/installers/bashrc.py
code_manager/installers/cmake.py
code_manager/installers/command.py
code_manager/installers/cp.py
code_manager/installers/emacs.py
code_manager/installers/gradle.py
code_manager/installers/ld.py
code_manager/installers/ln.py
code_manager/installers/make.py
code_manager/installers/maven.py
code_manager/installers/nodejs.py
code_manager/installers/path.py
code_manager/installers/pip.py
code_manager/installers/script.py
code_manager/installers/setup_py.py
code_manager/utils/__init__.py
code_manager/utils/contextmanagers.py
code_manager/utils/importing.py
code_manager/utils/lazy_property.py
code_manager/utils/logger.py
code_manager/utils/path_utils.py
code_manager/utils/printing.py
code_manager/utils/process.py
code_manager/utils/read_input.py
code_manager/utils/setenv.py
code_manager/utils/strings.py
code_manager/utils/utils.py
tests/__init__.py
tests/depender_test.py
tests/downloader_test.py
tests/marging_packages_test.py
tests/utils_test.py
CodeManager-1.0.0.dist-info/LICENSE
CodeManager-1.0.0.dist-info/METADATA
CodeManager-1.0.0.dist-info/WHEEL
CodeManager-1.0.0.dist-info/entry_points.txt
CodeManager-1.0.0.dist-info/top_level.txt
CodeManager-1.0.0.dist-info/RECORD
