Metadata-Version: 2.1
Name: CodeManager
Version: 1.0.0
Summary: Utility for automatic downloading, compiling and  installing softaware from internet.
Home-page: https://github.com/palikar/code_manager
Author: Stanislav Arnaudov
Author-email: stanislav_ts@abv.bg
License: GNU General Public License v3.0
Keywords: package code manager utility installation downloading compiling
Platform: UNKNOWN
Classifier: Development Status :: 3 - Alpha
Classifier: Intended Audience :: Developers
Classifier: Natural Language :: English
Classifier: License :: OSI Approved :: GNU General Public License v3 (GPLv3)
Classifier: Operating System :: POSIX :: Linux
Classifier: Programming Language :: Python :: 3.3
Classifier: Programming Language :: Python :: 3.4
Classifier: Programming Language :: Python :: 3.5
Classifier: Programming Language :: Python :: 3.6
Classifier: Topic :: Software Development :: Libraries :: Python Modules
Classifier: Topic :: System :: Archiving :: Mirroring
Classifier: Topic :: System :: Archiving :: Packaging
Classifier: Topic :: System :: Installation/Setup
